train_delay/__init__.py
train_delay/auth_data.py
train_delay/train_data.py
train_delay/train_delay_tracker.py
train_delay/db/schema.sql
train_delay-1.0.0.dist-info/licenses/LICENSE
train_delay-1.0.0.dist-info/METADATA
train_delay-1.0.0.dist-info/WHEEL
train_delay-1.0.0.dist-info/top_level.txt
train_delay-1.0.0.dist-info/RECORD
