Metadata-Version: 2.4
Name: train_delay
Version: 1.0.0
Summary: TrainDelay is a Python package for tracking train delays at various stations using the Deutsche Bahn API. It collects real-time train data, processes delay information, and stores it in a MySQL database for further analysis
Author-email: Michael <michael-development@outlook.de>
License-File: LICENSE
Requires-Dist: deutsche_bahn_api==1.1.0
Requires-Dist: mysql-connector==2.2.9
Dynamic: license-file
